resolution.py
resolution-0.0.1.dist-info/LICENSE
resolution-0.0.1.dist-info/METADATA
resolution-0.0.1.dist-info/WHEEL
resolution-0.0.1.dist-info/top_level.txt
resolution-0.0.1.dist-info/RECORD
