Metadata-Version: 2.1
Name: resolution
Version: 0.0.1
Summary: Resolution.
Author-email: Yan Kuang <YTKme@Outlook.com>
Project-URL: Homepage, https://github.com/YTKme/Python-Resolution
Project-URL: Bug Tracker, https://github.com/YTKme/Python-Resolution/issues
Classifier: Programming Language :: Python :: 3
Classifier: License :: OSI Approved :: MIT License
Classifier: Operating System :: OS Independent
Requires-Python: >=3.7
License-File: LICENSE
